flask_nosql/__init__.py
flask_nosql/memcache.py
flask_nosql/mongodb.py
flask_nosql/redis.py
Flask_NoSQL-0.1.0.dist-info/METADATA
Flask_NoSQL-0.1.0.dist-info/WHEEL
Flask_NoSQL-0.1.0.dist-info/top_level.txt
Flask_NoSQL-0.1.0.dist-info/RECORD
